exectools/__init__.py
exectools/handler.py
exectools/tools_basic.py
exectools/tools_coroutine.py
exectools/tools_decorator.py
exectools/tools_excel.py
exec_tools-0.0.24.dist-info/LICENSE
exec_tools-0.0.24.dist-info/METADATA
exec_tools-0.0.24.dist-info/WHEEL
exec_tools-0.0.24.dist-info/top_level.txt
exec_tools-0.0.24.dist-info/RECORD
