Metadata-Version: 2.1
Name: exec-tools
Version: 0.0.24
Summary: Some Tools.
Home-page: https://github.com/Supplayer/exec_tools.git
Author: Supplayer
Author-email: x254724521@hotmail.com
License: UNKNOWN
Platform: UNKNOWN
Classifier: Programming Language :: Python :: 3
Classifier: License :: OSI Approved :: MIT License
Classifier: Operating System :: OS Independent
Requires-Python: >=3.6
License-File: LICENSE
Requires-Dist: pandas
Requires-Dist: openpyxl
